{
  "indexed": {
    "date-parts": [
      [
        2022,
        4,
        5
      ]
    ],
    "date-time": "2022-04-05T15:33:11Z",
    "timestamp": 1649172791207
  },
  "reference-count": 0,
  "publisher": "Anadolu Universitesi Bilim ve Teknoloji Dergisi C : Yasam Bilimleri ve Biyoteknoloji",
  "issue": "1",
  "content-domain": {
    "domain": [],
    "crossmark-restriction": false
  },
  "short-container-title": [
    "BTDC"
  ],
  "DOI": "10.18036/btdc.01000",
  "type": "journal-article",
  "created": {
    "date-parts": [
      [
        2016,
        5,
        13
      ]
    ],
    "date-time": "2016-05-13T07:24:29Z",
    "timestamp": 1463124269000
  },
  "source": "Crossref",
  "is-referenced-by-count": 0,
  "title": [
    "Lead Biosorption by a Moderately Halophile Penicillium sp. Isolated from Çamalti Saltern in Turkey"
  ],
  "prefix": "10.18036",
  "volume": "5",
  "author": [
    {
      "given": "KIYMET",
      "family": "GÜVEN",
      "sequence": "first",
      "affiliation": []
    },
    {
      "given": "ELİF",
      "family": "KORCAN",
      "sequence": "additional",
      "affiliation": []
    },
    {
      "given": "SEMRA",
      "family": "MALKOÇ",
      "sequence": "additional",
      "affiliation": []
    },
    {
      "given": "MİNE",
      "family": "AYDIN KURÇ",
      "sequence": "additional",
      "affiliation": []
    },
    {
      "given": "ALAETTİN",
      "family": "GÜVEN",
      "sequence": "additional",
      "affiliation": []
    }
  ],
  "member": "7404",
  "published-online": {
    "date-parts": [
      [
        2016,
        5,
        13
      ]
    ]
  },
  "container-title": [
    "ANADOLU UNIVERSITY JOURNAL OF SCIENCE AND TECHNOLOGY –C Life Sciences and Biotechnology"
  ],
  "original-title": [],
  "deposited": {
    "date-parts": [
      [
        2016,
        11,
        23
      ]
    ],
    "date-time": "2016-11-23T14:33:25Z",
    "timestamp": 1479911605000
  },
  "score": 1,
  "resource": {
    "primary": {
      "URL": "http://dergipark.gov.tr/doi/10.18036/btdc.01000"
    }
  },
  "subtitle": [],
  "short-title": [],
  "issued": {
    "date-parts": [
      [
        2016,
        5,
        13
      ]
    ]
  },
  "references-count": 0,
  "journal-issue": {
    "issue": "1",
    "published-online": {
      "date-parts": [
        [
          2016
        ]
      ]
    }
  },
  "URL": "https://doi.org/10.18036/btdc.01000",
  "relation": {},
  "ISSN": [
    "2146-0213",
    "2146-0264"
  ],
  "issn-type": [
    {
      "value": "2146-0213",
      "type": "electronic"
    },
    {
      "value": "2146-0264",
      "type": "print"
    }
  ],
  "subject": [],
  "published": {
    "date-parts": [
      [
        2016,
        5,
        13
      ]
    ]
  }
}