{
  "indexed": {
    "date-parts": [
      [
        2022,
        3,
        31
      ]
    ],
    "date-time": "2022-03-31T22:54:26Z",
    "timestamp": 1648767266523
  },
  "reference-count": 13,
  "publisher": "China Science Publishing & Media Ltd.",
  "issue": "12",
  "content-domain": {
    "domain": [],
    "crossmark-restriction": false
  },
  "short-container-title": [
    "Chinese Journal of Eco-Agriculture"
  ],
  "published-print": {
    "date-parts": [
      [
        2013,
        3,
        4
      ]
    ]
  },
  "DOI": "10.3724/sp.j.1011.2012.01700",
  "type": "journal-article",
  "created": {
    "date-parts": [
      [
        2013,
        3,
        4
      ]
    ],
    "date-time": "2013-03-04T16:44:34Z",
    "timestamp": 1362415474000
  },
  "page": "1700-1705",
  "source": "Crossref",
  "is-referenced-by-count": 0,
  "title": [
    "Halophyte resources and community characteristics in different habitats with subsurface pipe drainage system"
  ],
  "prefix": "10.3724",
  "volume": "20",
  "author": [
    {
      "given": "Wen-Hui",
      "family": "WANG",
      "sequence": "first",
      "affiliation": []
    },
    {
      "given": "Hui-Tao",
      "family": "LIU",
      "sequence": "additional",
      "affiliation": []
    },
    {
      "given": "Feng-Jiao",
      "family": "MA",
      "sequence": "additional",
      "affiliation": []
    },
    {
      "given": "Li-Pu",
      "family": "HAN",
      "sequence": "additional",
      "affiliation": []
    },
    {
      "given": "Peng",
      "family": "LIU",
      "sequence": "additional",
      "affiliation": []
    },
    {
      "given": "Li",
      "family": "XU",
      "sequence": "additional",
      "affiliation": []
    },
    {
      "given": "Li-Mei",
      "family": "TAN",
      "sequence": "additional",
      "affiliation": []
    },
    {
      "given": "Shu-Hui",
      "family": "YU",
      "sequence": "additional",
      "affiliation": []
    },
    {
      "given": "Jin-Tong",
      "family": "LIU",
      "sequence": "additional",
      "affiliation": []
    }
  ],
  "member": "2026",
  "reference": [
    {
      "key": "10.3724/SP.J.1011.2012.01700-1"
    },
    {
      "key": "10.3724/SP.J.1011.2012.01700-2"
    },
    {
      "key": "10.3724/SP.J.1011.2012.01700-3"
    },
    {
      "key": "10.3724/SP.J.1011.2012.01700-4"
    },
    {
      "key": "10.3724/SP.J.1011.2012.01700-5"
    },
    {
      "key": "10.3724/SP.J.1011.2012.01700-6"
    },
    {
      "key": "10.3724/SP.J.1011.2012.01700-7"
    },
    {
      "key": "10.3724/SP.J.1011.2012.01700-8"
    },
    {
      "key": "10.3724/SP.J.1011.2012.01700-9"
    },
    {
      "key": "10.3724/SP.J.1011.2012.01700-10"
    },
    {
      "key": "10.3724/SP.J.1011.2012.01700-11"
    },
    {
      "key": "10.3724/SP.J.1011.2012.01700-12"
    },
    {
      "key": "10.3724/SP.J.1011.2012.01700-13"
    }
  ],
  "container-title": [
    "Chinese Journal of Eco-Agriculture"
  ],
  "original-title": [],
  "language": "en",
  "link": [
    {
      "URL": "http://www.ecoagri.ac.cn/article/exportPdf?id=20121221",
      "content-type": "unspecified",
      "content-version": "vor",
      "intended-application": "similarity-checking"
    }
  ],
  "deposited": {
    "date-parts": [
      [
        2022,
        3,
        8
      ]
    ],
    "date-time": "2022-03-08T07:44:26Z",
    "timestamp": 1646725466000
  },
  "score": 1,
  "resource": {
    "primary": {
      "URL": "http://www.ecoagri.ac.cn/cn/article/doi/10.3724/SP.J.1011.2012.01700"
    }
  },
  "subtitle": [
    "Halophyte resources and community characteristics in different habitats with subsurface pipe drainage system"
  ],
  "short-title": [],
  "issued": {
    "date-parts": [
      [
        2013,
        3,
        4
      ]
    ]
  },
  "references-count": 13,
  "journal-issue": {
    "issue": "12",
    "published-print": {
      "date-parts": [
        [
          2012,
          12,
          20
        ]
      ]
    }
  },
  "URL": "https://doi.org/10.3724/sp.j.1011.2012.01700",
  "relation": {},
  "ISSN": [
    "1671-3990"
  ],
  "issn-type": [
    {
      "value": "1671-3990",
      "type": "print"
    }
  ],
  "subject": [],
  "published": {
    "date-parts": [
      [
        2013,
        3,
        4
      ]
    ]
  }
}